{"/_app":"pages/_app.js","/_meta":"pages/_meta.js","/_error":"pages/_error.js","/faq":"pages/faq.html","/guides/_meta":"pages/guides/_meta.js","/guides/contributing":"pages/guides/contributing.html","/guides/environments":"pages/guides/environments.html","/guides/operations":"pages/guides/operations.html","/guides/security":"pages/guides/security.html","/architecture":"pages/architecture.html","/api":"pages/api.js","/aivm":"pages/aivm.html","/protocol":"pages/protocol.html","/":"pages/index.html","/guides/scripts":"pages/guides/scripts.html","/how-it-works":"pages/how-it-works.html","/ios":"pages/ios.html","/guides/database":"pages/guides/database.html","/guides/deploy":"pages/guides/deploy.html","/_document":"pages/_document.js","/404":"pages/404.html"}